Workbook

Sheet Revenue Dashboard
A1: SINHA'S GmbH — Revenue & Occupancy Dashboard
B3: PORTFOLIO KPIs | F3: REVENUE KPIs (CHF)
B4: Total Properties Listed | C4: =COUNTA('Property Lookup'!B4:B500) -> 144 | F4: Total Monthly Rent (all bookings) | G4: =SUM('Revenue Tracker'!Z5:Z1004) -> 0
B5: Occupied Properties | C5: =COUNTIF('Property Lookup'!I4:I500,"OCCUPIED") -> 106 | F5: Total Invoiced | G5: =SUM('Revenue Tracker'!AS5:AS1004) -> 0
B6: Vacant Properties | C6: =COUNTIF('Property Lookup'!I4:I500,"VACANT") -> 7 | F6: Total Collected | G6: =SUM('Revenue Tracker'!AT5:AT1004) -> 0
B7: Own Properties | C7: =COUNTIF('Property Lookup'!H4:H500,"OWN") -> 22 | F7: Total Balance Due | G7: =SUM('Revenue Tracker'!AU5:AU1004) -> 0
B8: Sublet Properties | C8: =COUNTIF('Property Lookup'!H4:H500,"SUB") -> 122 | F8: Total Deposits Held | G8: =SUMPRODUCT(('Revenue Tracker'!AC5:AC1004)-('Revenue Tracker'!AK5:AK1004)) -> 0
B10: GUEST KPIs | F10: CLEANING & ANCILLARY (CHF)
B11: Total Bookings | C11: =COUNTA('Revenue Tracker'!B5:B1004) -> 0 | F11: Total Cleaning Due | G11: =SUM('Revenue Tracker'!#REF!) -> #REF!
B12: Unique Guests (Profiles) | C12: =COUNTA('Guest Profiles'!B5:B1004) -> 0 | F12: Total Cleaning Paid | G12: =SUM('Revenue Tracker'!#REF!) -> #REF!
B13: Business Stays | C13: =COUNTIF('Revenue Tracker'!X5:X1004,"Business") -> 0 | F13: Total City Tax | G13: =SUM('Revenue Tracker'!AQ5:AQ1004) -> 0
B14: Leisure Stays | C14: =COUNTIF('Revenue Tracker'!X5:X1004,"Leisure") -> 0 | F14: Total Commission | G14: =SUM('Revenue Tracker'!AR5:AR1004) -> 0
B17: DATABASE SCHEMA — KEY RELATIONSHIPS
B18: Primary Key (PK) | C18: GUEST ID | E18: Unique identifier for each guest in Guest Profiles sheet
B19: Foreign Key (FK-1) | C19: GUEST ID | E19: Links Revenue Tracker → Guest Profiles
B20: Foreign Key (FK-2) | C20: PROPERTY ID | E20: Links Revenue Tracker → Property Lookup
B21: Composite Key | C21: GUEST ID + PROPERTY ID | E21: Uniquely identifies each booking in Revenue Tracker
B22: Booking Ref | C22: SR-YYYY-NNNN | E22: Sequential booking reference tied to a Property ID
B23: Client Code | C23: SG-YYYY-NNNN | E23: SINHA'S internal client code per guest

Sheet Guest Profiles
A1: SINHA'S GmbH — Guest / Client Profile Database
A2: Primary Key: GUEST ID | Neugutstrasse 16, 8304 Wallisellen, Zürich | Confidential
A3: GUEST IDENTIFICATION (PK: Guest ID) | I3: CONTACT DETAILS | P3: ADDRESS — SWITZERLAND | V3: ORIGIN — INDIA / HOME COUNTRY | AB3: COMPANY / EMPLOYER | AH3: INTERNAL / ADMIN
A4: S.No. | B4: Guest ID (PK) | C4: SINHA'S Client Code | D4: Title (Mr/Mrs/Ms/Dr/Prof) | E4: First Name | F4: Last Name / Family Name | G4: Full Name (as per Passport/ID) | H4: Date of Birth (DD.MM.YYYY) | I4: Email ID (Primary) | J4: Email ID (Secondary) | K4: Mobile Number (with Country Code) | L4: WhatsApp Number (with Country Code) | M4: Landline / Office Phone | N4: Preferred Language | O4: Preferred Contact Method | P4: Street & House No. (CH) | Q4: PLZ (Postcode) | R4: City / Ort (CH) | S4: Canton | T4: Country of Residence | U4: Permit Type (L/B/C/G/Other) | V4: Nationality / Citizenship | W4: Passport / ID Number | X4: Place of Origin in India (City) | Y4: State / Region (India) | Z4: Home Address (India / Abroad) | AA4: PIN Code / Postal Code (Home) | AB4: Company / Employer Name | AC4: Designation / Job Title | AD4: Company Address (Switzerland) | AE4: Booking Channel / Partner | AF4: Travel Purpose (Business/Leisure) | AG4: Guest Type (Corp/ Family/ Student/ Intern) | AH4: Guest Type (VIP/ Non-VIP) | AI4: Tier (Diamond/ Gold/ Standard/ Risk) | AJ4: Remarks / Special Notes | AK4: Date Added (DD.MM.YYYY)
A5: =ROW()-4 -> 1
A6: =ROW()-4 -> 2
A7: =ROW()-4 -> 3
A8: =ROW()-4 -> 4
A9: =ROW()-4 -> 5
A10: =ROW()-4 -> 6
A11: =ROW()-4 -> 7
A12: =ROW()-4 -> 8
A13: =ROW()-4 -> 9
A14: =ROW()-4 -> 10
A15: =ROW()-4 -> 11
A16: =ROW()-4 -> 12
... A204: =ROW()-4 -> 200

Sheet Property Lookup
A1: SINHA'S GmbH — Property Master Lookup (FK Reference)
A2: Source: Property_Details_V4 | Property ID is the Foreign Key linking Guest Profiles ↔ Revenue Tracker
A3: S.No. | B3: Property ID (FK) | C3: Full Address | D3: City | E3: PLZ | F3: Rooms | G3: SQM | H3: Own/Sublet | I3: Status | J3: OTA/NON-OTA | K3: Property Type | L3: Canton
A4: 1 | B4: AF10-4L-1.5-APA-SUB-8050-ZH-ZH-CH | C4: Affolternstrasse 10, 8050 Zürich | D4: Zürich | E4: 8050 | F4: 1.5 | G4: 40 | H4: SUB | I4: VACANT
A5: 2 | B5: AL26A-2L-1.5-APA-SUB-8304-WS-ZH-CH | C5: Alte Winterthurerstrasse 26A, 8304 Wallisellen | D5: Wallisellen | E5: 8304 | F5: 1.5 | G5: 35 | H5: SUB | I5: OCCUPIED
A6: 3 | B6: AL26A-4L-1.5-APA-SUB-8304-WS-ZH-CH | C6: Alte Winterthurerstrasse 26A, 8304 Wallisellen | D6: Wallisellen | E6: 8304 | F6: 1.5 | G6: 45 | H6: SUB | I6: OCCUPIED
A7: 4 | B7: AL2-3L-2.5-APA-SUB-8953-DK-ZH-CH | C7: Altbergstrasse 2, 8953 Dietikon | D7: Dietikon | E7: 8953 | F7: 2.5 | G7: 50 | H7: SUB | I7: OCCUPIED
A8: 5 | B8: AL45-1L-3.5-APA-SUB-8134-AW-ZH-CH | C8: Albisstrasse 45, 8134 Adliswil | D8: Adliswil | E8: 8134 | F8: 3.5 | G8: 65 | H8: SUB | I8: OCCUPIED
A9: 6 | B9: AL55-4L-2.5-APA-SUB-8134-AW-ZH-CH | C9: Albisstrasse 55, 8134 Adliswil | D9: Adliswil | E9: 8134 | F9: 2.5 | G9: 50 | H9: SUB | I9: OCCUPIED
A10: 7 | B10: AP21-3L-2.5-APA-SUB-8051-ZH-ZH-CH | C10: Aprikosenstrasse 21, 8051 Zürich | D10: Zürich | E10: 8051 | F10: 2.5 | G10: 60 | H10: SUB | I10: OCCUPIED
A11: 8 | B11: AU2-1L-2.5-APA-OWN-8153-RL-ZH-CH | C11: Ausserdorfstrasse 2, 8153 Rümlang | D11: Rümlang | E11: 8153 | F11: 2.5 | G11: 60 | H11: OWN | I11: OCCUPIED
A12: 9 | B12: AU41-1L-3.5-APA-SUB-8045-ZH-ZH-CH | C12: Austrasse -S7 41, 8045 Zürich | D12: Zürich | E12: 8045 | F12: 3.5 | G12: 80 | H12: SUB | I12: OCCUPIED
A13: 10 | B13: AU41-3L-3.5-APA-SUB-8045-ZH-ZH-CH | C13: Austrasse-S5 41, 8045 Zürich | D13: Zürich | E13: 8045 | F13: 3.5 | G13: 80 | H13: SUB | I13: OCCUPIED
A14: 11 | B14: AU41-4L-3.5-APA-SUB-8045-ZH-ZH-CH | C14: Austrasse-S6 41, 8045 Zürich | D14: Zürich | E14: 8045 | F14: 3.5 | G14: 80 | H14: SUB | I14: OCCUPIED
A15: 12 | B15: AU41-GL-3.5-APA-SUB-8045-ZH-ZH-CH | C15: Austrasse-S4 41, 8045 Zürich | D15: Zürich | E15: 8045 | F15: 3.5 | G15: 80 | H15: SUB | I15: OCCUPIED
... A19: 16 | B19: DE3-2L-3.5-APA-SUB-3073-GU-BE-CH | C19: Dennigkofenweg 3, 3073 Gümligen/ Bern | D19: Gümligen/ Bern | E19: 3073 | F19: 3.5 | G19: 1250 | H19: SUB | I19: SURRENDERED
A20: 17 | B20: DE3-GL-3.5-APA-SUB-3073-GU-BE-CH | C20: Dennigkofenweg 3, 3073 Gümligen/ Bern | D20: Gümligen/ Bern | E20: 3073 | F20: 3.5 | H20: SUB | I20: SURRENDERED
A21: 18 | B21: FR5A-2L-4.5-APA-SUB-8304-WS-ZH-CH | C21: Friedenstrasse 5a, 8304 Wallisellen | D21: Wallisellen | E21: 8304 | F21: 4.5 | G21: 80 | H21: SUB | I21: OCCUPIED
A22: 19 | B22: GR11-3L-4.5-APA-SUB-8304-WS-ZH-CH | C22: Grabenstrasse 11, 8304 Wallisellen | D22: Wallisellen | E22: 8304 | F22: 4.5 | G22: 95 | H22: SUB | I22: OCCUPIED
A23: 20 | B23: GR45A-1L-2.5-APA-SUB-4052-BS-BS-CH | C23: Grosspeterstrasse 45a, 4052 Basel | D23: Basel | E23: 4052 | F23: 2.5 | G23: 60 | H23: SUB | I23: OCCUPIED
A24: 21 | B24: HI60-1L-3.5-APA-SUB-8051-ZH-ZH-CH | C24: Hirzenbachstrasse 60, 8051 Zürich | D24: Zürich | E24: 8051 | F24: 3.5 | G24: 70 | H24: SUB | I24: OCCUPIED
A25: 22 | B25: HI86-GL-2.5-APA-SUB-8051-ZH-ZH-CH | C25: Hirzenbachstrasse 86, 8051 Zürich | D25: Zürich | E25: 8051 | F25: 2.5 | H25: SUB | I25: SURRENDERED
A26: 23 | B26: HO15-4L-3.5-APA-SUB-8045-ZH-ZH-CH | C26: Hopfenstrasse -S3 15, 8045 Zürich | D26: Zürich | E26: 8045 | F26: 3.5 | G26: 80 | H26: SUB | I26: OCCUPIED
A27: 24 | B27: LE16-3L-3.5-APA-SUB-8600-DD-ZH-CH | C27: Leepüntstrasse 16, 8600 Dübendorf | D27: Dübendorf | E27: 8600 | F27: 3.5 | G27: 97.1 | H27: SUB | I27: OCCUPIED
A28: 25 | B28: LE16-2L-1-APA-SUB-8600-DD-ZH-CH | C28: Leepüntstrasse 16, 8600 Dübendorf | D28: Dübendorf | E28: 8600 | F28: 1 | G28: 36 | H28: SUB | I28: OCCUPIED
A29: 26 | B29: LE18-1L-2.5-APA-SUB-8600-DD-ZH-CH | C29: Leepüntstrasse 18, 8600 Dübendorf | D29: Dübendorf | E29: 8600 | F29: 2.5 | G29: 53.7 | H29: SUB | I29: OCCUPIED
A30: 27 | B30: LE18-2L-2.5-APA-SUB-8600-DD-ZH-CH | C30: Leepüntstrasse 18, 8600 Dübendorf | D30: Dübendorf | E30: 8600 | F30: 2.5 | G30: 53.7 | H30: SUB | I30: OCCUPIED
A31: 28 | B31: LE18-3L-2.5-APA-SUB-8600-DD-ZH-CH-A | C31: Leepüntstrasse 18, 8600 Dübendorf | D31: Dübendorf | E31: 8600 | F31: 2.5 | G31: 53.7 | H31: SUB | I31: OCCUPIED
A32: 29 | B32: LE18-3L-2.5-APA-SUB-8600-DD-ZH-CH-B | C32: Leepüntstrasse 18, 8600 Dübendorf | D32: Dübendorf | E32: 8600 | F32: 2.5 | H32: SUB | I32: OCCUPIED
A33: 30 | B33: LE20-1L-2.5-APA-SUB-8600-DD-ZH-CH | C33: Leepüntstrasse 20, 8600 Dübendorf | D33: Dübendorf | E33: 8600 | F33: 2.5 | G33: 53.7 | H33: SUB | I33: OCCUPIED
A34: 31 | B34: LE20-2L-2.5-APA-SUB-8600-DD-ZH-CH | C34: Leepüntstrasse 20, 8600 Dübendorf | D34: Dübendorf | E34: 8600 | F34: 2.5 | G34: 53.7 | H34: SUB | I34: OCCUPIED
A35: 32 | B35: LI8-GL-1-APA-SUB-8304-WS-ZH-CH | C35: Lindenstrasse 8, 8304 Wallisellen | D35: Wallisellen | E35: 8304 | F35: 1 | G35: 16 | H35: SUB | I35: OCCUPIED
A36: 33 | B36: ME14-3L-2.5-APA-SUB-8304-WS-ZH-CH | C36: Melchrütistrasse 14, 8304 Wallisellen | D36: Wallisellen | E36: 8304 | F36: 2.5 | G36: 70 | H36: SUB | I36: OCCUPIED
A37: 34 | B37: NE75-2L-3.5-APA-SUB-8304-WS-ZH-CH | C37: Neue Winterthurerstrasse 75, 8304 Wallisellen | D37: Wallisellen | E37: 8304 | F37: 3.5 | G37: 70 | H37: SUB | I37: OCCUPIED
A38: 35 | B38: RI143-1L-2.5-APA-SUB-4058-BS-BS-CH | C38: Riehenring 143, 4058 Basel | D38: Basel | E38: 4058 | F38: 2.5 | G38: 55 | H38: SUB | I38: OCCUPIED
A39: 36 | B39: RI143-5L-2.5-APA-SUB-4058-BS-BS-CH | C39: Riehenring 143, 4058 Basel | D39: Basel | E39: 4058 | F39: 2.5 | G39: 55 | H39: SUB | I39: OCCUPIED
A40: 37 | B40: RI167-4L-3.5-APA-SUB-4058-BS-BS-CH | C40: Riehenstrasse 167, 4058 Basel | D40: Basel | E40: 4058 | F40: 3.5 | G40: 60 | H40: SUB | I40: OCCUPIED
A41: 38 | B41: RI16-2L-3.5-APA-SUB-6300-ZG-ZG-CH | C41: Riedmatweg 16, 6300 Zug | D41: Zug | E41: 6300 | F41: 3.5 | H41: SUB | I41: SURRENDERED
A42: 39 | B42: SC1A-2L-2.5-APA-SUB-8304-WS-ZH-CH | C42: Schutzenstrasse 1a, 8304 Wallisellen | D42: Wallisellen | E42: 8304 | F42: 2.5 | G42: 68 | H42: SUB | I42: OCCUPIED
A43: 40 | B43: SE64-2L-2.5-APA-OWN-8052-ZH-ZH-CH | C43: Seebacherstrasse 64, 8052 Zürich | D43: Zürich | E43: 8052 | F43: 2.5 | G43: 60 | H43: OWN | I43: OCCUPIED
A44: 41 | B44: SE66-3L-4.5-APA-OWN-8052-ZH-ZH-CH | C44: Seebacherstrasse 66, 8052 Zürich | D44: Zürich | E44: 8052 | F44: 4.5 | G44: 90 | H44: OWN | I44: OCCUPIED
A45: 42 | B45: ST16-BL-1.5-APA-OWN-8903-BD-ZH-CH | C45: Stöckenstrasse 16, 8903 Birmensdorf | D45: Birmensdorf | E45: 8903 | F45: 1.5 | G45: 35 | H45: OWN | I45: OCCUPIED
A46: 43 | B46: ST16-GL-1.5-APA-OWN-8903-BD-ZH-CH | C46: Stöckenstrasse -S3 16, 8903 Birmensdorf | D46: Birmensdorf | E46: 8903 | F46: 1.5 | G46: 65 | H46: OWN | I46: OCCUPIED
A47: 44 | B47: ST35-GL-1-APA-SUB-8003-ZH-ZH-CH | C47: Steinstrasse (S-2) 35, 8003 Zürich | D47: Zürich | E47: 8003 | F47: 1 | G47: 25 | H47: SUB | I47: OCCUPIED
A48: 45 | B48: ST36-3L-1.5-APA-SUB-4051-BS-BS-CH-A | C48: Steinenvorstadt 36, 4051 Basel | D48: Basel | E48: 4051 | F48: 1.5 | G48: 35 | H48: SUB | I48: OCCUPIED
A49: 46 | B49: ST36-3L-1.5-APA-SUB-4051-BS-BS-CH-B | C49: Steinenvorstadt 36, 4051 Basel | D49: Basel | E49: 4051 | F49: 1.5 | G49: 35 | H49: SUB | I49: OCCUPIED
A50: 47 | B50: ST3-GL-1.5-APA-SUB-8903-BD-ZH-CH | C50: Stöckenstrasse 3, 8903 Birmensdorf | D50: Birmensdorf | E50: 8903 | F50: 1.5 | H50: SUB | I50: SURRENDERED
A51: 48 | B51: ST40A-GL-2-APA-OWN-8903-BD-ZH-CH | C51: Stöckenstrasse 40a, 8903 Birmensdorf | D51: Birmensdorf | E51: 8903 | F51: 2 | G51: 50 | H51: OWN | I51: OCCUPIED
A52: 49 | B52: ST71-2L-2.5-APA-SUB-4051-BS-BS-CH | C52: Steinenvorstadt 71, 4051 Basel | D52: Basel | E52: 4051 | F52: 2.5 | H52: SUB | I52: SURRENDERED
A53: 50 | B53: TA47-1L-4.5-APA-OWN-8152-GB-ZH-CH | C53: Talackerstrasse 47, 8152 Glattbrugg | D53: Glattbrugg | E53: 8152 | F53: 4.5 | G53: 110 | H53: OWN | I53: OCCUPIED
A54: 51 | B54: TR24-1L-2.5-APA-SUB-8050-ZH-ZH-CH | C54: Tramstrasse 24, 8050 Zürich | D54: Zürich | E54: 8050 | F54: 2.5 | G54: 60 | H54: SUB | I54: OCCUPIED
A55: 52 | B55: WA156-14L-3.5-APA-OWN-8152-GB-ZH-CH | C55: Wallisellerstrasse 156, 8152 Glattbrugg | D55: Glattbrugg | E55: 8152 | F55: 3.5 | G55: 75 | H55: OWN | I55: OCCUPIED
A56: 53 | B56: WA156-9L-2.5-APA-SUB-8152-GB-ZH-CH | C56: Wallisellerstrasse 156, 8152 Glattbrugg | D56: Glattbrugg | E56: 8152 | F56: 2.5 | G56: 55 | H56: SUB | I56: OCCUPIED
A57: 54 | B57: WI651-1L-2.5-APA-SUB-8051-ZH-ZH-CH | C57: Winterthurerstrasse 651, 8051 Zürich | D57: Zürich | E57: 8051 | F57: 2.5 | H57: SUB | I57: SURRENDERED
A58: 55 | B58: WI9-GL-2.5-APA-SUB-8304-WS-ZH-CH | C58: Wiesgasse 9, 8304 Wallisellen | D58: Wallisellen | E58: 8304 | F58: 2.5 | H58: SUB | I58: SURRENDERED
A59: 56 | B59: ST35-GLL-1-APA-SUB-8003-ZH-ZH-CH | C59: Steinstrasse 35, 8003 Zürich | D59: Zürich | E59: 8003 | F59: 1 | G59: 25 | H59: SUB | I59: VACANT
A60: 57 | B60: AR2-2M-4.5-APA-SUB-8304-WS-ZH-CH | C60: Archengässli 2, 8304 Wallisellen | D60: Wallisellen | E60: 8304 | F60: 4.5 | G60: 80 | H60: SUB | I60: OCCUPIED
A61: 58 | B61: BA27-2M-4.5-APA-SUB-8800-TH-ZH-CH | C61: Bahnhofstrasse 27, 8800 Thalwil | D61: Thalwil | E61: 8800 | F61: 4.5 | H61: SUB | I61: SURRENDERED
A62: 59 | B62: ED7-BM-3.5-APA-OWN-7270-DP-GR-CH | C62: Edenstrasse 7, 7270 Davos Platz | D62: Davos Platz | E62: 7270 | F62: 3.5 | G62: 50 | H62: OWN | I62: OCCUPIED
A63: 60 | B63: HO65A-2M-2.5-APA-SUB-8135-LA-BS-CH | C63: Höflistrasse 65a, 8135 Langnau am Albis | D63: Langnau am Albis | E63: 8135 | F63: 2.5 | G63: 50 | H63: SUB | I63: VACANT
A64: 61 | B64: LE16-1M-3.5-APA-SUB-8600-DD-ZH-CH | C64: Leepüntstrasse 16, 8600 Dübendorf | D64: Dübendorf | E64: 8600 | F64: 3.5 | G64: 77.4 | H64: SUB | I64: OCCUPIED
A65: 62 | B65: LE18-2M-3.5-APA-SUB-8600-DD-ZH-CH | C65: Leepüntstrasse 18, 8600 Dübendorf | D65: Dübendorf | E65: 8600 | F65: 3.5 | G65: 77 | H65: SUB | I65: OCCUPIED
A66: 63 | B66: LE20-2M-3.5-APA-SUB-8600-DD-ZH-CH | C66: Leepüntstrasse 20, 8600 Dübendorf | D66: Dübendorf | E66: 8600 | F66: 3.5 | G66: 77.4 | H66: SUB | I66: OCCUPIED
A67: 64 | B67: TR24-GM-1.5-APA-SUB-8050-ZH-ZH-CH | C67: Tramstrasse 24, 8050 Zürich | D67: Zürich | E67: 8050 | F67: 1.5 | G67: 35 | H67: SUB | I67: OCCUPIED
A68: 65 | B68: UB11-1M-1-APA-SUB-8953-DK-ZH-CH | C68: Überlandstrasse 11, 8953 Dietikon | D68: Dietikon | E68: 8953 | F68: 1 | G68: 30 | H68: SUB | I68: OCCUPIED
A69: 66 | B69: UB465-2M-2.5-APA-SUB-8051-ZH-ZH-CH | C69: Überlandstrasse 465, 8051 Zürich | D69: Zürich | E69: 8051 | F69: 2.5 | G69: 55 | H69: SUB | I69: OCCUPIED
A70: 67 | B70: UB465-7M-1.5-APA-SUB-8051-ZH-ZH-CH | C70: Überlandstrasse 465, 8051 Zürich | D70: Zürich | E70: 8051 | F70: 1.5 | G70: 35 | H70: SUB | I70: OCCUPIED
A71: 68 | B71: WI55-GM-1.5-APA-OWN-8135-LA-ZH-CH | C71: Wildenbühlstrasse 55, 8135 Langnau am Albis | D71: Langnau am Albis | E71: 8135 | F71: 1.5 | G71: 27 | H71: OWN | I71: OCCUPIED
A72: 69 | B72: WI9-GM-2.5-APA-SUB-8304-WS-ZH-CH | C72: Wiesgasse 9, 8304 Wallisellen | D72: Wallisellen | E72: 8304 | F72: 2.5 | H72: SUB | I72: SURRENDERED
A73: 70 | B73: NE37-2ML-3.5-APA-SUB-8304-WS-ZH-CH | C73: Neugutstrasse 37, 8304 Wallisellen | D73: Wallisellen | E73: 8304 | F73: 3.5 | G73: 70 | H73: SUB | I73: OCCUPIED
A74: 71 | B74: RO130-1ML-1-APA-SUB-8051-ZH-ZH-CH | C74: Roswiesenstrasse 130, 8051 Zürich | D74: Zürich | E74: 8051 | F74: 1 | H74: SUB | I74: SURRENDERED
A75: 72 | B75: AL2-1MR-1.5-APA-SUB-8953-DK-ZH-CH | C75: Altbergstrasse 2, 8953 Dietikon | D75: Dietikon | E75: 8953 | F75: 1.5 | G75: 35 | H75: SUB | I75: VACANT
A76: 73 | B76: AL45-GMR-3.5-APA-SUB-8134-AW-ZH-CH | C76: Albisstrasse 45, 8134 Adliswil | D76: Adliswil | E76: 8134 | F76: 3.5 | G76: 65 | H76: SUB | I76: OCCUPIED
A77: 74 | B77: NE37-1MR-3.5-APA-OWN-8304-WS-ZH-CH | C77: Neugutstrasse 37, 8304 Wallisellen | D77: Wallisellen | E77: 8304 | F77: 3.5 | G77: 70 | H77: OWN | I77: OCCUPIED
A78: 75 | B78: AL18-1R-3.5-APA-SUB-8304-WS-ZH-CH | C78: Allmendstrasse 18, 8304 Wallisellen | D78: Wallisellen | E78: 8304 | F78: 3.5 | H78: SUB | I78: SURRENDERED
A79: 76 | B79: AL26-2R-4.5-APA-SUB-8304-WS-ZH-CH | C79: Alte Winterthurerstrasse 26, 8304 Wallisellen | D79: Wallisellen | E79: 8304 | F79: 4.5 | G79: 110 | H79: SUB | I79: OCCUPIED
A80: 77 | B80: AL2-3R-2.5-APA-SUB-8953-DK-ZH-CH | C80: Altbergstrasse 2, 8953 Dietikon | D80: Dietikon | E80: 8953 | F80: 2.5 | G80: 50 | H80: SUB | I80: OCCUPIED
A81: 78 | B81: AU41-1R-3.5-APA-SUB-8045-ZH-ZH-CH | C81: Austrasse-S2 41, 8045 Zürich | D81: Zürich | E81: 8045 | F81: 3.5 | G81: 80 | H81: SUB | I81: VACANT
A82: 79 | B82: AU41-2R-3.5-APA-SUB-8045-ZH-ZH-CH | C82: Austrasse -S9 41, 8045 Zürich | D82: Zürich | E82: 8045 | F82: 3.5 | G82: 80 | H82: SUB | I82: VACANT
A83: 80 | B83: AU41-3R-3.5-APA-SUB-8045-ZH-ZH-CH | C83: Austrasse-S8 41, 8045 Zürich | D83: Zürich | E83: 8045 | F83: 3.5 | G83: 80 | H83: SUB | I83: OCCUPIED
A84: 81 | B84: AU41-4R-3.5-APA-SUB-8045-ZH-ZH-CH | C84: Austrasse-S3 41, 8045 Zürich | D84: Zürich | E84: 8045 | F84: 3.5 | G84: 80 | H84: SUB | I84: OCCUPIED
A85: 82 | B85: AU41-GR-3.5-APA-SUB-8045-ZH-ZH-CH | C85: Austrasse-S1 41, 8045 Zürich | D85: Zürich | E85: 8045 | F85: 3.5 | G85: 80 | H85: SUB
A86: 83 | B86: BI37A-2R-3.5-APA-SUB-8600-DD-ZH-CH | C86: Birchlenstrasse 37 a, 8600 Dübendorf | D86: Dübendorf | E86: 8600 | F86: 3.5 | G86: 70 | H86: SUB | I86: OCCUPIED
A87: 84 | B87: BI37B-GR-4.5-APA-SUB-8600-DD-ZH-CH | C87: Birchlenstrasse 37 b, 8600 Dübendorf | D87: Dübendorf | E87: 8600 | F87: 4.5 | G87: 85 | H87: SUB | I87: OCCUPIED
A88: 85 | B88: DO24-1R-5.5-APA-OWN-8906-BO-ZH-CH | C88: Dorfstrasse 24, 8906 Bonstatten | D88: Bonstatten | E88: 8906 | F88: 5.5 | G88: 130 | H88: OWN | I88: OCCUPIED
A89: 86 | B89: EG19-GR-2.5-APA-OWN-4054-BS-BS-CH | C89: Eggfluhstrasse 19, 4054 Basel | D89: Basel | E89: 4054 | F89: 2.5 | G89: 60 | H89: OWN | I89: OCCUPIED
A90: 87 | B90: EG19-GR-1.5-APA-OWN-4054-BS-BS-CH | C90: Eggfluhstrasse 19, 4054 Basel | D90: Basel | E90: 4054 | F90: 1.5 | G90: 40 | H90: OWN | I90: OCCUPIED
A91: 88 | B91: FO7-GR-3.5-APA-SUB-8304-WS-ZH-CH | C91: Föhrlibuckstrasse 7, 8304 Wallisellen | D91: Wallisellen | E91: 8304 | F91: 3.5 | H91: SUB | I91: SURRENDERED
A92: 89 | B92: HO15-2R-3.5-APA-SUB-8045-ZH-ZH-CH | C92: Hopfenstrasse -S1 15, 8045 Zürich | D92: Zürich | E92: 8045 | F92: 3.5 | G92: 80 | H92: SUB | I92: OCCUPIED
A93: 90 | B93: HO15-3R-3.5-APA-SUB-8045-ZH-ZH-CH | C93: Hopfenstrasse -S2 15, 8045 Zürich | D93: Zürich | E93: 8045 | F93: 3.5 | G93: 80 | H93: SUB
A94: 91 | B94: HO65A-3R-3.5-APA-SUB-8135-LA-ZH-CH | C94: Höflistrasse 65a, 8135 Langnau am Albis | D94: Langnau am Albis | E94: 8135 | F94: 3.5 | G94: 70 | H94: SUB | I94: OCCUPIED
A95: 92 | B95: KI4-GR-2-APA-SUB-8600-DD-ZH-CH | C95: Kirchbachstrasse 4, 8600 Dübendorf | D95: Dübendorf | E95: 8600 | F95: 2 | G95: 50 | H95: SUB | I95: OCCUPIED
A96: 93 | B96: LA5-2R-3.5-APA-OWN-8152-GB-ZH-CH | C96: Lattenwiessenstrasse 5, 8152 Glattbrugg | D96: Glattbrugg | E96: 8152 | F96: 3.5 | G96: 75 | H96: OWN | I96: OCCUPIED
A97: 94 | B97: LE16-1R-2.5-APA-SUB-8600-DD-ZH-CH | C97: Leepüntstrasse 16, 8600 Dübendorf | D97: Dübendorf | E97: 8600 | F97: 2.5 | G97: 53.7 | H97: SUB | I97: OCCUPIED
A98: 95 | B98: LE16-2R-2.5-APA-SUB-8600-DD-ZH-CH | C98: Leepüntstrasse 16, 8600 Dübendorf | D98: Dübendorf | E98: 8600 | F98: 2.5 | G98: 53.7 | H98: SUB | I98: OCCUPIED
A99: 96 | B99: LE16-3R-2.5-APA-SUB-8600-DD-ZH-CH | C99: Leepüntstrasse 16, 8600 Dübendorf | D99: Dübendorf | E99: 8600 | F99: 2.5 | G99: 53.7 | H99: SUB | I99: OCCUPIED
A100: 97 | B100: LE18-1R-1.5-APA-SUB-8600-DD-ZH-CH | C100: Leepüntstrasse 18, 8600 Dübendorf | D100: Dübendorf | E100: 8600 | F100: 1.5 | G100: 36 | H100: SUB | I100: OCCUPIED
A101: 98 | B101: LE18-GR-1.5-APA-SUB-8600-DD-ZH-CH | C101: Leepüntstrasse 18, 8600 Dübendorf | D101: Dübendorf | E101: 8600 | F101: 1.5 | G101: 36 | H101: SUB | I101: OCCUPIED
A102: 99 | B102: LE20-3R-3.5-APA-SUB-8600-DD-ZH-CH | C102: Leepüntstrasse 20, 8600 Dübendorf | D102: Dübendorf | E102: 8600 | F102: 3.5 | G102: 97.1 | H102: SUB | I102: OCCUPIED
A103: 100 | B103: LE20-1R-1.5-APA-SUB-8600-DD-ZH-CH | C103: Leepüntstrasse 20, 8600 Dübendorf | D103: Dübendorf | E103: 8600 | F103: 1.5 | G103: 36 | H103: SUB | I103: OCCUPIED
...

Sheet Revenue Tracker
A1: SINHA'S GmbH — Revenue Tracker
A2: Composite Key: GUEST ID (FK → Guest Profiles) + PROPERTY ID (FK → Property Lookup) | All amounts in CHF
A3: KEYS (Guest ID + Property ID) | E3: GUEST SUMMARY | J3: PROPERTY SUMMARY | Q3: STAY DETAILS | Y3: REVENUE & FINANCIALS (CHF) | AV3: STATUS & NOTES
A4: S.No. | B4: Booking Ref No. | C4: Guest ID (FK → Guest Profiles) | D4: Property ID (FK → Property Lookup) | E4: Guest Full Name | F4: Nationality | G4: Company / Employer | H4: Mobile | I4: Email | J4: Property Address | K4: City | L4: Rooms | M4: SQM | N4: Own / Sublet | O4: Property Type | P4: Booking Channel | Q4: Move Within SINHA'S | R4: Check-in Date | S4: Check-out Date | T4: Guest Nights | U4: No. of Guests | V4: Children (under 16) | W4: Stay Type (Short/Long) | X4: Purpose (Business/ Leisure) | Y4: Currency | Z4: Monthly Rent (CHF) | AA4: Pro-Rate Daily Rate (CHF) | AB4: Total Rent (CHF) | AC4: Deposit (CHF) | AD4: Deposit Paid Date | AE4: Cleaning Paid (CHF) | AF4: Cleaning Due (CHF) | AG4: Additional Cleaning( if applicable) | AH4: Reimbursement | AI4: Pet Fee | AJ4: Net Deposit | AK4: Deposit Returned (CHF) | AL4: Deposit Return Date | AM4: Deposit Refund Source (Own/Sublet Bank) | AN4: SINHA'S Internal Deposit Adjustments | AO4: Guest IBAN / Account Nr (for Refund) | AP4: Notice Period Rent / Deposit Adjustments | AQ4: City Tax (CHF) | AR4: Commission (CHF) | AS4: Total Invoice (CHF) | AT4: Total Paid (CHF) | AU4: Balance Due (CHF) | AV4: Payment Method | AW4: Payment Status | AX4: Booking Status | AY4: Remarks | AZ4: Last Updated
A5: =ROW()-4 -> 1 | T5: =IF(AND(R5<>"",S5<>""),S5-R5,"") | Y5: CHF | AA5: =IF(Z5<>"",ROUND(Z5/30,2),"") | AB5: =IF(AND(Z5<>"",T5<>""),ROUND(Z5/30*T5,2),"") | AS5: =IF(AB5<>"",AB5+IF(#REF!<>"",#REF!,0)+IF(AQ5<>"",AQ5,0)+IF(AR5<>"",AR5,0),"") | AU5: =IF(AS5<>"",AS5-IF(AT5<>"",AT5,0),"")
A6: =ROW()-4 -> 2 | T6: =IF(AND(R6<>"",S6<>""),S6-R6,"") | Y6: CHF | AA6: =IF(Z6<>"",ROUND(Z6/30,2),"") | AB6: =IF(AND(Z6<>"",T6<>""),ROUND(Z6/30*T6,2),"") | AS6: =IF(AB6<>"",AB6+IF(#REF!<>"",#REF!,0)+IF(AQ6<>"",AQ6,0)+IF(AR6<>"",AR6,0),"") | AU6: =IF(AS6<>"",AS6-IF(AT6<>"",AT6,0),"")
A7: =ROW()-4 -> 3 | T7: =IF(AND(R7<>"",S7<>""),S7-R7,"") | Y7: CHF | AA7: =IF(Z7<>"",ROUND(Z7/30,2),"") | AB7: =IF(AND(Z7<>"",T7<>""),ROUND(Z7/30*T7,2),"") | AS7: =IF(AB7<>"",AB7+IF(#REF!<>"",#REF!,0)+IF(AQ7<>"",AQ7,0)+IF(AR7<>"",AR7,0),"") | AU7: =IF(AS7<>"",AS7-IF(AT7<>"",AT7,0),"")
A8: =ROW()-4 -> 4 | T8: =IF(AND(R8<>"",S8<>""),S8-R8,"") | Y8: CHF | AA8: =IF(Z8<>"",ROUND(Z8/30,2),"") | AB8: =IF(AND(Z8<>"",T8<>""),ROUND(Z8/30*T8,2),"") | AS8: =IF(AB8<>"",AB8+IF(#REF!<>"",#REF!,0)+IF(AQ8<>"",AQ8,0)+IF(AR8<>"",AR8,0),"") | AU8: =IF(AS8<>"",AS8-IF(AT8<>"",AT8,0),"")
A9: =ROW()-4 -> 5 | T9: =IF(AND(R9<>"",S9<>""),S9-R9,"") | Y9: CHF | AA9: =IF(Z9<>"",ROUND(Z9/30,2),"") | AB9: =IF(AND(Z9<>"",T9<>""),ROUND(Z9/30*T9,2),"") | AS9: =IF(AB9<>"",AB9+IF(#REF!<>"",#REF!,0)+IF(AQ9<>"",AQ9,0)+IF(AR9<>"",AR9,0),"") | AU9: =IF(AS9<>"",AS9-IF(AT9<>"",AT9,0),"")
A10: =ROW()-4 -> 6 | T10: =IF(AND(R10<>"",S10<>""),S10-R10,"") | Y10: CHF | AA10: =IF(Z10<>"",ROUND(Z10/30,2),"") | AB10: =IF(AND(Z10<>"",T10<>""),ROUND(Z10/30*T10,2),"") | AS10: =IF(AB10<>"",AB10+IF(#REF!<>"",#REF!,0)+IF(AQ10<>"",AQ10,0)+IF(AR10<>"",AR10,0),"") | AU10: =IF(AS10<>"",AS10-IF(AT10<>"",AT10,0),"")
A11: =ROW()-4 -> 7 | T11: =IF(AND(R11<>"",S11<>""),S11-R11,"") | Y11: CHF | AA11: =IF(Z11<>"",ROUND(Z11/30,2),"") | AB11: =IF(AND(Z11<>"",T11<>""),ROUND(Z11/30*T11,2),"") | AS11: =IF(AB11<>"",AB11+IF(#REF!<>"",#REF!,0)+IF(AQ11<>"",AQ11,0)+IF(AR11<>"",AR11,0),"") | AU11: =IF(AS11<>"",AS11-IF(AT11<>"",AT11,0),"")
A12: =ROW()-4 -> 8 | T12: =IF(AND(R12<>"",S12<>""),S12-R12,"") | Y12: CHF | AA12: =IF(Z12<>"",ROUND(Z12/30,2),"") | AB12: =IF(AND(Z12<>"",T12<>""),ROUND(Z12/30*T12,2),"") | AS12: =IF(AB12<>"",AB12+IF(#REF!<>"",#REF!,0)+IF(AQ12<>"",AQ12,0)+IF(AR12<>"",AR12,0),"") | AU12: =IF(AS12<>"",AS12-IF(AT12<>"",AT12,0),"")
A13: =ROW()-4 -> 9 | T13: =IF(AND(R13<>"",S13<>""),S13-R13,"") | Y13: CHF | AA13: =IF(Z13<>"",ROUND(Z13/30,2),"") | AB13: =IF(AND(Z13<>"",T13<>""),ROUND(Z13/30*T13,2),"") | AS13: =IF(AB13<>"",AB13+IF(#REF!<>"",#REF!,0)+IF(AQ13<>"",AQ13,0)+IF(AR13<>"",AR13,0),"") | AU13: =IF(AS13<>"",AS13-IF(AT13<>"",AT13,0),"")
A14: =ROW()-4 -> 10 | T14: =IF(AND(R14<>"",S14<>""),S14-R14,"") | Y14: CHF | AA14: =IF(Z14<>"",ROUND(Z14/30,2),"") | AB14: =IF(AND(Z14<>"",T14<>""),ROUND(Z14/30*T14,2),"") | AS14: =IF(AB14<>"",AB14+IF(#REF!<>"",#REF!,0)+IF(AQ14<>"",AQ14,0)+IF(AR14<>"",AR14,0),"") | AU14: =IF(AS14<>"",AS14-IF(AT14<>"",AT14,0),"")
A15: =ROW()-4 -> 11 | T15: =IF(AND(R15<>"",S15<>""),S15-R15,"") | Y15: CHF | AA15: =IF(Z15<>"",ROUND(Z15/30,2),"") | AB15: =IF(AND(Z15<>"",T15<>""),ROUND(Z15/30*T15,2),"") | AS15: =IF(AB15<>"",AB15+IF(#REF!<>"",#REF!,0)+IF(AQ15<>"",AQ15,0)+IF(AR15<>"",AR15,0),"") | AU15: =IF(AS15<>"",AS15-IF(AT15<>"",AT15,0),"")
A16: =ROW()-4 -> 12 | T16: =IF(AND(R16<>"",S16<>""),S16-R16,"") | Y16: CHF | AA16: =IF(Z16<>"",ROUND(Z16/30,2),"") | AB16: =IF(AND(Z16<>"",T16<>""),ROUND(Z16/30*T16,2),"") | AS16: =IF(AB16<>"",AB16+IF(#REF!<>"",#REF!,0)+IF(AQ16<>"",AQ16,0)+IF(AR16<>"",AR16,0),"") | AU16: =IF(AS16<>"",AS16-IF(AT16<>"",AT16,0),"")
... A204: =ROW()-4 -> 200 | T204: =IF(AND(R204<>"",S204<>""),S204-R204,"") | Y204: CHF | AA204: =IF(Z204<>"",ROUND(Z204/30,2),"") | AB204: =IF(AND(Z204<>"",T204<>""),ROUND(Z204/30*T204,2),"") | AS204: =IF(AB204<>"",AB204+IF(#REF!<>"",#REF!,0)+IF(AQ204<>"",AQ204,0)+IF(AR204<>"",AR204,0),"") | AU204: =IF(AS204<>"",AS204-IF(AT204<>"",AT204,0),"")

Sheet Data Dictionary
A1: SINHA'S GmbH — Database Schema — Field Definitions & Key Relationships
A2: Sheet | B2: Field Name | C2: Column | D2: Key Type | E2: Data Type | F2: Description | G2: Example / Format
A3: Guest Profiles | B3: Guest ID | C3: B | D3: PK | E3: Text | F3: System-generated unique guest identifier | G3: 23696522
A4: Guest Profiles | B4: SINHA'S Client Code | C4: C | D4: — | E4: Text | F4: Internal client code: SG-YYYY-NNNN | G4: SG-2026-0001
A5: Guest Profiles | B5: Full Name | C5: G | D5: — | E5: Text | F5: Legal name as per Passport/ID | G5: Mr. Rajeev Sinha
A6: Guest Profiles | B6: Email (Primary) | C6: I | D6: — | E6: Text | F6: Primary email for correspondence | G6: guest@company.com
A7: Guest Profiles | B7: Mobile Number | C7: K | D7: — | E7: Text | F7: Mobile with international code | G7: +91 98765 43210
A8: Guest Profiles | B8: WhatsApp Number | C8: L | D8: — | E8: Text | F8: WhatsApp-registered number | G8: +41 79 123 45 67
A9: Guest Profiles | B9: Place of Origin (India) | C9: X | D9: — | E9: Text | F9: Home city in India | G9: Bengaluru
A10: Guest Profiles | B10: Company / Employer | C10: AB | D10: — | E10: Text | F10: Corporate client name | G10: Tech Mahindra Limited
A12: Property Lookup | B12: Property ID | C12: B | D12: PK/FK | E12: Text | F12: Smart Property ID from Property Master | G12: AU41-1L-3.5-APA-SUB-8045-ZH-ZH-CH
A13: Property Lookup | B13: Full Address | C13: C | D13: — | E13: Text | F13: Complete property address | G13: Austrasse 41, 8045 Zürich
A14: Property Lookup | B14: Own/Sublet | C14: H | D14: — | E14: Text | F14: Ownership status | G14: OWN / SUB
... A26: Revenue Tracker | B26: Balance Due (CHF) | C26: AP | D26: — | E26: Formula | F26: Total Invoice minus Total Paid | G26: 0.00
